dz_lib/__init__.py
dz_lib/bivariate/__init__.py
dz_lib/bivariate/data.py
dz_lib/bivariate/distributions.py
dz_lib/univariate/__init__.py
dz_lib/univariate/data.py
dz_lib/univariate/distributions.py
dz_lib/univariate/histograms.py
dz_lib/univariate/mda.py
dz_lib/univariate/mds.py
dz_lib/univariate/metrics.py
dz_lib/univariate/nmf.py
dz_lib/univariate/unmix.py
dz_lib/utils/__init__.py
dz_lib/utils/data.py
dz_lib/utils/encode.py
dz_lib/utils/fonts.py
dz_lib/utils/formats.py
dz_lib/utils/matrices.py
dz_lib-1.5.6.dist-info/licenses/LICENSE.txt
dz_lib-1.5.6.dist-info/METADATA
dz_lib-1.5.6.dist-info/WHEEL
dz_lib-1.5.6.dist-info/top_level.txt
dz_lib-1.5.6.dist-info/RECORD
