Metadata-Version: 2.4
Name: dz_lib
Version: 1.5.6
Home-page: https://github.com/nielrya4/dz_lib
Author: Ryan Nielsen
Author-email: nielrya4@isu.edu
License: MIT
Classifier: Programming Language :: Python :: 3
Classifier: License :: OSI Approved :: MIT License
Classifier: Operating System :: OS Independent
License-File: LICENSE.txt
Requires-Dist: openpyxl
Requires-Dist: matplotlib
Requires-Dist: pyexcel
Requires-Dist: numpy
Requires-Dist: pandas
Requires-Dist: plotly
Requires-Dist: scipy
Requires-Dist: PeakUtils
Requires-Dist: scikit-learn
Requires-Dist: setuptools
Dynamic: author
Dynamic: author-email
Dynamic: classifier
Dynamic: description
Dynamic: description-content-type
Dynamic: home-page
Dynamic: license
Dynamic: license-file
Dynamic: requires-dist
